galaxy/__init__.py
galaxy/project_galaxy_containers.py
galaxy/containers/__init__.py
galaxy/containers/docker.py
galaxy/containers/docker_decorators.py
galaxy/containers/docker_model.py
galaxy/containers/docker_swarm.py
galaxy_containers-22.1.1.dist-info/LICENSE
galaxy_containers-22.1.1.dist-info/METADATA
galaxy_containers-22.1.1.dist-info/WHEEL
galaxy_containers-22.1.1.dist-info/entry_points.txt
galaxy_containers-22.1.1.dist-info/top_level.txt
galaxy_containers-22.1.1.dist-info/RECORD
